jt/pyjava.cfg
jt/pyjava/__about__.py
jt/pyjava/__config__.py
jt/pyjava/__init__.py
jt/pyjava/_main.py
jt/pyjava/find_dll.py
jt/pyjava/_platform/__init__.py
jt/pyjava/_platform/_android.py
jt/pyjava/_platform/_linux.py
jt/pyjava/_platform/_macos.py
jt/pyjava/_platform/_windows.py
jt/pyjava/_pyjava/__init__.py
jt/pyjava/_pyjava/_constants.py
jt/pyjava/_pyjava/_exceptions.py
jt/pyjava/_pyjava/_javawrapper.py
jt/pyjava/_pyjava/_jclass.py
jt/pyjava/_pyjava/_jfield.py
jt/pyjava/_pyjava/_jmethod.py
jt/pyjava/_pyjava/_jvm.py
jt/pyjava/_pyjava/_main.py
jt/pyjava/_pyjava/_typemanager.py
jt/pyjava/_pyjava/_util.py
jt/pyjava/_pyjava/_typehandler/__init__.py
jt/pyjava/_pyjava/_typehandler/_base_handler.py
jt/pyjava/_pyjava/_typehandler/array_handler.py
jt/pyjava/_pyjava/_typehandler/boolean_handler.py
jt/pyjava/_pyjava/_typehandler/byte_handler.py
jt/pyjava/_pyjava/_typehandler/char_handler.py
jt/pyjava/_pyjava/_typehandler/class_handler.py
jt/pyjava/_pyjava/_typehandler/double_handler.py
jt/pyjava/_pyjava/_typehandler/float_handler.py
jt/pyjava/_pyjava/_typehandler/int_handler.py
jt/pyjava/_pyjava/_typehandler/long_handler.py
jt/pyjava/_pyjava/_typehandler/object_handler.py
jt/pyjava/_pyjava/_typehandler/short_handler.py
jt/pyjava/_pyjava/_typehandler/string_handler.py
jt/pyjava/_pyjava/_typehandler/void_handler.py
jtypes.pyjava-0.1.5b8.dist-info/LICENSE
jtypes.pyjava-0.1.5b8.dist-info/METADATA
jtypes.pyjava-0.1.5b8.dist-info/WHEEL
jtypes.pyjava-0.1.5b8.dist-info/top_level.txt
jtypes.pyjava-0.1.5b8.dist-info/RECORD
