Metadata-Version: 2.1
Name: jtypes.pyjava
Version: 0.1.5b8
Summary: A Python to Java bridge (ctypes/cffi-based PyJava).
Author: Adam Karpierz
Author-email: adam@karpierz.net
Maintainer: Adam Karpierz
Maintainer-email: adam@karpierz.net
License: MIT License ; https://opensource.org/license/mit
Project-URL: Homepage, https://pypi.org/project/jtypes.pyjava/
Project-URL: Documentation, https://jtypespyjava.readthedocs.io/
Project-URL: Download, https://pypi.org/project/jtypes.pyjava/
Project-URL: Source, https://github.com/karpierz/jtypes.pyjava
Project-URL: Issues, https://github.com/karpierz/jtypes.pyjava/issues
Keywords: jni,jvm,jtypes,jt,jpype,jep,pyjnius,jpy,javabridge,pyjava,jcc,py4j,jython,java,pythonjava,rubicon-java
Platform: any
Classifier: Development Status :: 4 - Beta
Classifier: Intended Audience :: Developers
Classifier: License :: OSI Approved :: MIT License
Classifier: Operating System :: OS Independent
Classifier: Natural Language :: Polish
Classifier: Programming Language :: Python
Classifier: Programming Language :: Python :: 3
Classifier: Programming Language :: Python :: 3.9
Classifier: Programming Language :: Python :: 3.10
Classifier: Programming Language :: Python :: 3.11
Classifier: Programming Language :: Python :: 3.12
Classifier: Programming Language :: Python :: 3.13
Classifier: Programming Language :: Python :: 3 :: Only
Classifier: Programming Language :: Python :: Implementation :: CPython
Classifier: Programming Language :: Python :: Implementation :: PyPy
Classifier: Programming Language :: Java
Classifier: Topic :: Software Development :: Libraries :: Python Modules
Classifier: Topic :: Software Development :: Libraries :: Java Libraries
Requires-Python: <4.0.0,>=3.9.0
License-File: LICENSE
Requires-Dist: setuptools>=75.3.0
Requires-Dist: pkg-about>=1.2.2
Requires-Dist: jni>=1.1.0b4
Requires-Dist: jvm>=0.6.0b5
Provides-Extra: doc
Requires-Dist: Sphinx>=7.4.7; extra == "doc"
Requires-Dist: sphinx-toolbox>=3.8.1; extra == "doc"
Requires-Dist: sphinx-tabs>=3.4.5; extra == "doc"
Requires-Dist: sphinx-copybutton>=0.5.2; extra == "doc"
Requires-Dist: sphinxcontrib-spelling>=8.0.0; extra == "doc"
Requires-Dist: sphinx-lint>=1.0.0; extra == "doc"
Requires-Dist: restructuredtext-lint>=1.4.0; extra == "doc"
Requires-Dist: nbsphinx>=0.9.5; extra == "doc"
Provides-Extra: test
Requires-Dist: deepdiff>=8.0.1; extra == "test"
Requires-Dist: rich>=13.9.4; extra == "test"
